AUTHORS.rst
CONTRIBUTING.rst
HISTORY.rst
LICENSE
MANIFEST.in
README.md
setup.cfg
setup.py
django_async_image_upload/__init__.py
django_async_image_upload/admin.py
django_async_image_upload/apps.py
django_async_image_upload/docs.py
django_async_image_upload/exceptions.py
django_async_image_upload/models.py
django_async_image_upload/permissions.py
django_async_image_upload/selectors.py
django_async_image_upload/serializers.py
django_async_image_upload/settings.py
django_async_image_upload/urls.py
django_async_image_upload/utils.py
django_async_image_upload/viewsets.py
django_async_image_upload.egg-info/PKG-INFO
django_async_image_upload.egg-info/SOURCES.txt
django_async_image_upload.egg-info/dependency_links.txt
django_async_image_upload.egg-info/not-zip-safe
django_async_image_upload.egg-info/requires.txt
django_async_image_upload.egg-info/top_level.txt
django_async_image_upload/static/css/django_async_image_upload.css
django_async_image_upload/static/js/django_async_image_upload.js
django_async_image_upload/templates/django_async_image_upload/base.html
django_async_image_upload/test_utils/__init__.py
django_async_image_upload/test_utils/test_app/__init__.py
django_async_image_upload/test_utils/test_app/admin.py
django_async_image_upload/test_utils/test_app/apps.py
django_async_image_upload/test_utils/test_app/models.py
django_async_image_upload/test_utils/test_app/migrations/__init__.py