Metadata-Version: 2.1
Name: django-async-image-upload
Version: 0.1.0
Summary: Your project description goes here
Home-page: https://github.com/kokospapa8/django-async-image-upload
Author: django-async-image-upload
Author-email: kokos.papa8@gmail.com
License: Apache Software License 2.0
Keywords: django-async-image-upload
Platform: UNKNOWN
Classifier: Development Status :: 3 - Alpha
Classifier: Framework :: Django :: 3.1
Classifier: Intended Audience :: Developers
Classifier: License :: OSI Approved :: BSD License
Classifier: Natural Language :: English
Classifier: Programming Language :: Python :: 3
Classifier: Programming Language :: Python :: 3.5
Classifier: Programming Language :: Python :: 3.6
Requires-Python: >=3.6
